oiseau/__init__.py
oiseau/cpp/mesh.cpp
cpp.cpython-310-x86_64-linux-gnu.so
oiseau-0.1.0.dist-info/WHEEL
oiseau-0.1.0.dist-info/METADATA
oiseau-0.1.0.dist-info/RECORD
